zepo_external_services/__init__.py
zepo_external_services/core/__init__.py
zepo_external_services/core/base_provider.py
zepo_external_services/core/config.py
zepo_external_services/core/exceptions.py
zepo_external_services/core/factory.py
zepo_external_services/directory/__init__.py
zepo_external_services/email/__init__.py
zepo_external_services/email/aws_ses_provider.py
zepo_external_services/email/base.py
zepo_external_services/queue/__init__.py
zepo_external_services/secrets/__init__.py
zepo_external_services/sms/__init__.py
zepo_external_services/sms/base.py
zepo_external_services/sms/bird_provider.py
zepo_external_services/sms/twilio_provider.py
zepo_external_services/storage/__init__.py
zepo_external_services-0.1.3.dist-info/METADATA
zepo_external_services-0.1.3.dist-info/WHEEL
zepo_external_services-0.1.3.dist-info/RECORD
